Workbook

Sheet DB
B1: GASTO POR ALUNO DO EF - SIOPE
A2: KEY | B2: COD_ENTE | C2: MUN | D2: NUM_ANO | E2: NUM_PERI | F2: COD_INDI | G2: COD_EXIB | H2: CATEG | I2: INDICADOR | J2: VAL_INDI
A3: =C3&D3&G3 -> Águas Formosas20151.1 | B3: 3100906 | C3: Águas Formosas | D3: 2015 | E3: 1 | F3: 24 | G3: 1.1 | H3: Indicador legal | I3: 1.1 - Percentual de aplicação das receitas de impostos e transferências vinculadas à educação em MDE (mínimo de 25% para estados, DF e municípios) | J3: 0.282
A4: =C4&D4&G4 -> Águas Formosas20151.2 | B4: 3100906 | C4: Águas Formosas | D4: 2015 | E4: 1 | F4: 67 | G4: 1.2 | H4: Indicador legal | I4: 1.2 - Percentual de aplicação do FUNDEB na remuneração dos profissionais da educação (mínimo de 70%) - Inciso XXII, Portaria Conjunta MGI/MF/CGU Nº 33 de30-08-2023 | J4: 0.7194
A5: =C5&D5&G5 -> Águas Formosas20151.3 | B5: 3100906 | C5: Águas Formosas | D5: 2015 | E5: 1 | F5: 68 | G5: 1.3 | H5: Indicador legal | I5: 1.3 - Percentual de aplicação do FUNDEB em despesas com MDE, que não remuneração dos profissionais da educação (máximo de 30%) | J5: 0.2728
A6: =C6&D6&G6 -> Águas Formosas20152.1 | B6: 3100906 | C6: Águas Formosas | D6: 2015 | E6: 1 | F6: 28 | G6: 2.1 | H6: Indicador de dispêndio financeiro | I6: 2.1 - Percentual dos recursos do FUNDEB aplicados na educação infantil | J6: 0.2206
A7: =C7&D7&G7 -> Águas Formosas20152.2 | B7: 3100906 | C7: Águas Formosas | D7: 2015 | E7: 1 | F7: 29 | G7: 2.2 | H7: Indicador de dispêndio financeiro | I7: 2.2 - Percentual dos recursos do FUNDEB aplicados no ensino fundamental | J7: 0.6747
A8: =C8&D8&G8 -> Águas Formosas20152.4 | B8: 3100906 | C8: Águas Formosas | D8: 2015 | E8: 1 | F8: 31 | G8: 2.4 | H8: Indicador de dispêndio financeiro | I8: 2.4 - Percentual das despesas com educação infantil em relação à despesa total com educação | J8: 0.3711
A9: =C9&D9&G9 -> Águas Formosas20152.5 | B9: 3100906 | C9: Águas Formosas | D9: 2015 | E9: 1 | F9: 32 | G9: 2.5 | H9: Indicador de dispêndio financeiro | I9: 2.5 - Percentual das despesas com ensino fundamental em relação à despesa total com educação | J9: 0.5985
A10: =C10&D10&G10 -> Águas Formosas20152.8 | B10: 3100906 | C10: Águas Formosas | D10: 2015 | E10: 1 | F10: 35 | G10: 2.8 | H10: Indicador de dispêndio financeiro | I10: 2.8 - Percentual das despesas em educação em relação às despesas de todas as áreas | J10: 0.3087
A11: =C11&D11&G11 -> Águas Formosas20154.1 | B11: 3100906 | C11: Águas Formosas | D11: 2015 | E11: 1 | F11: 44 | G11: 4.1 | H11: Indicador de investimento por aluno | I11: 4.1 - Investimento educacional por aluno da educação infantil | J11: 4090.75
A12: =C12&D12&G12 -> Águas Formosas20154.10 | B12: 3100906 | C12: Águas Formosas | D12: 2015 | E12: 1 | F12: 58 | G12: 4.10 | H12: Indicador de investimento por aluno | I12: 4.10 - Despesa com professores por aluno da educação básica | J12: 2413.48
A13: =C13&D13&G13 -> Águas Formosas20154.11 | B13: 3100906 | C13: Águas Formosas | D13: 2015 | E13: 1 | F13: 59 | G13: 4.11 | H13: Indicador de investimento por aluno | I13: 4.11 - Despesas com profissionais não docentes da área educacional por aluno da educação básica | J13: 1824.29
A14: =C14&D14&G14 -> Águas Formosas20154.2 | B14: 3100906 | C14: Águas Formosas | D14: 2015 | E14: 1 | F14: 45 | G14: 4.2 | H14: Indicador de investimento por aluno | I14: 4.2 - Investimento educacional por aluno do ensino fundamental | J14: 10390.98
... A33: =C33&D33&G33 -> Bertópolis20151.3 | B33: 3106606 | C33: Bertópolis | D33: 2015 | E33: 1 | F33: 68 | G33: 1.3 | H33: Indicador legal | I33: 1.3 - Percentual de aplicação do FUNDEB em despesas com MDE, que não remuneração dos profissionais da educação (máximo de 30%) | J33: 0.1565
A34: =C34&D34&G34 -> Bertópolis20152.1 | B34: 3106606 | C34: Bertópolis | D34: 2015 | E34: 1 | F34: 28 | G34: 2.1 | H34: Indicador de dispêndio financeiro | I34: 2.1 - Percentual dos recursos do FUNDEB aplicados na educação infantil
A35: =C35&D35&G35 -> Bertópolis20152.2 | B35: 3106606 | C35: Bertópolis | D35: 2015 | E35: 1 | F35: 29 | G35: 2.2 | H35: Indicador de dispêndio financeiro | I35: 2.2 - Percentual dos recursos do FUNDEB aplicados no ensino fundamental | J35: 0.7323
A36: =C36&D36&G36 -> Bertópolis20152.4 | B36: 3106606 | C36: Bertópolis | D36: 2015 | E36: 1 | F36: 31 | G36: 2.4 | H36: Indicador de dispêndio financeiro | I36: 2.4 - Percentual das despesas com educação infantil em relação à despesa total com educação | J36: 0.1928
A37: =C37&D37&G37 -> Bertópolis20152.5 | B37: 3106606 | C37: Bertópolis | D37: 2015 | E37: 1 | F37: 32 | G37: 2.5 | H37: Indicador de dispêndio financeiro | I37: 2.5 - Percentual das despesas com ensino fundamental em relação à despesa total com educação | J37: 0.7742
A38: =C38&D38&G38 -> Bertópolis20152.8 | B38: 3106606 | C38: Bertópolis | D38: 2015 | E38: 1 | F38: 35 | G38: 2.8 | H38: Indicador de dispêndio financeiro | I38: 2.8 - Percentual das despesas em educação em relação às despesas de todas as áreas | J38: 0.2224
A39: =C39&D39&G39 -> Bertópolis20154.1 | B39: 3106606 | C39: Bertópolis | D39: 2015 | E39: 1 | F39: 44 | G39: 4.1 | H39: Indicador de investimento por aluno | I39: 4.1 - Investimento educacional por aluno da educação infantil | J39: 4123.82
A40: =C40&D40&G40 -> Bertópolis20154.10 | B40: 3106606 | C40: Bertópolis | D40: 2015 | E40: 1 | F40: 58 | G40: 4.10 | H40: Indicador de investimento por aluno | I40: 4.10 - Despesa com professores por aluno da educação básica | J40: 4240.52
A41: =C41&D41&G41 -> Bertópolis20154.11 | B41: 3106606 | C41: Bertópolis | D41: 2015 | E41: 1 | F41: 59 | G41: 4.11 | H41: Indicador de investimento por aluno | I41: 4.11 - Despesas com profissionais não docentes da área educacional por aluno da educação básica | J41: 706.77
A42: =C42&D42&G42 -> Bertópolis20154.2 | B42: 3106606 | C42: Bertópolis | D42: 2015 | E42: 1 | F42: 45 | G42: 4.2 | H42: Indicador de investimento por aluno | I42: 4.2 - Investimento educacional por aluno do ensino fundamental | J42: 8207.5
A43: =C43&D43&G43 -> Bertópolis20154.8 | B43: 3106606 | C43: Bertópolis | D43: 2015 | E43: 1 | F43: 56 | G43: 4.8 | H43: Indicador de investimento por aluno | I43: 4.8 - Investimento educacional por aluno da educação básica | J43: 6853.99
A44: =C44&D44&G44 -> Bertópolis20154.9 | B44: 3106606 | C44: Bertópolis | D44: 2015 | E44: 1 | F44: 57 | G44: 4.9 | H44: Indicador de investimento por aluno | I44: 4.9 - Investimento educacional por aluno | J44: 6853.99
A45: =C45&D45&G45 -> Carlos Chagas20151.1 | B45: 3113701 | C45: Carlos Chagas | D45: 2015 | E45: 1 | F45: 24 | G45: 1.1 | H45: Indicador legal | I45: 1.1 - Percentual de aplicação das receitas de impostos e transferências vinculadas à educação em MDE (mínimo de 25% para estados, DF e municípios) | J45: 0.3021
A46: =C46&D46&G46 -> Carlos Chagas20151.2 | B46: 3113701 | C46: Carlos Chagas | D46: 2015 | E46: 1 | F46: 67 | G46: 1.2 | H46: Indicador legal | I46: 1.2 - Percentual de aplicação do FUNDEB na remuneração dos profissionais da educação (mínimo de 70%) - Inciso XXII, Portaria Conjunta MGI/MF/CGU Nº 33 de30-08-2023 | J46: 0.8752
... A89: =C89&D89&G89 -> Franciscópolis20151.3 | B89: 3126752 | C89: Franciscópolis | D89: 2015 | E89: 1 | F89: 68 | G89: 1.3 | H89: Indicador legal | I89: 1.3 - Percentual de aplicação do FUNDEB em despesas com MDE, que não remuneração dos profissionais da educação (máximo de 30%) | J89: 0.3469
A90: =C90&D90&G90 -> Franciscópolis20152.1 | B90: 3126752 | C90: Franciscópolis | D90: 2015 | E90: 1 | F90: 28 | G90: 2.1 | H90: Indicador de dispêndio financeiro | I90: 2.1 - Percentual dos recursos do FUNDEB aplicados na educação infantil
A91: =C91&D91&G91 -> Franciscópolis20152.2 | B91: 3126752 | C91: Franciscópolis | D91: 2015 | E91: 1 | F91: 29 | G91: 2.2 | H91: Indicador de dispêndio financeiro | I91: 2.2 - Percentual dos recursos do FUNDEB aplicados no ensino fundamental | J91: 0.692
A92: =C92&D92&G92 -> Franciscópolis20152.4 | B92: 3126752 | C92: Franciscópolis | D92: 2015 | E92: 1 | F92: 31 | G92: 2.4 | H92: Indicador de dispêndio financeiro | I92: 2.4 - Percentual das despesas com educação infantil em relação à despesa total com educação | J92: 0.1278
A93: =C93&D93&G93 -> Franciscópolis20152.5 | B93: 3126752 | C93: Franciscópolis | D93: 2015 | E93: 1 | F93: 32 | G93: 2.5 | H93: Indicador de dispêndio financeiro | I93: 2.5 - Percentual das despesas com ensino fundamental em relação à despesa total com educação | J93: 0.8378
A94: =C94&D94&G94 -> Franciscópolis20152.8 | B94: 3126752 | C94: Franciscópolis | D94: 2015 | E94: 1 | F94: 35 | G94: 2.8 | H94: Indicador de dispêndio financeiro | I94: 2.8 - Percentual das despesas em educação em relação às despesas de todas as áreas | J94: 0.2421
A95: =C95&D95&G95 -> Franciscópolis20154.1 | B95: 3126752 | C95: Franciscópolis | D95: 2015 | E95: 1 | F95: 44 | G95: 4.1 | H95: Indicador de investimento por aluno | I95: 4.1 - Investimento educacional por aluno da educação infantil | J95: 3594.3
A96: =C96&D96&G96 -> Franciscópolis20154.10 | B96: 3126752 | C96: Franciscópolis | D96: 2015 | E96: 1 | F96: 58 | G96: 4.10 | H96: Indicador de investimento por aluno | I96: 4.10 - Despesa com professores por aluno da educação básica | J96: 1722.39
A97: =C97&D97&G97 -> Franciscópolis20154.11 | B97: 3126752 | C97: Franciscópolis | D97: 2015 | E97: 1 | F97: 59 | G97: 4.11 | H97: Indicador de investimento por aluno | I97: 4.11 - Despesas com profissionais não docentes da área educacional por aluno da educação básica | J97: 1439.11
A98: =C98&D98&G98 -> Franciscópolis20154.2 | B98: 3126752 | C98: Franciscópolis | D98: 2015 | E98: 1 | F98: 45 | G98: 4.2 | H98: Indicador de investimento por aluno | I98: 4.2 - Investimento educacional por aluno do ensino fundamental | J98: 6533.76
A99: =C99&D99&G99 -> Franciscópolis20154.8 | B99: 3126752 | C99: Franciscópolis | D99: 2015 | E99: 1 | F99: 56 | G99: 4.8 | H99: Indicador de investimento por aluno | I99: 4.8 - Investimento educacional por aluno da educação básica | J99: 5895.48
A100: =C100&D100&G100 -> Franciscópolis20154.9 | B100: 3126752 | C100: Franciscópolis | D100: 2015 | E100: 1 | F100: 57 | G100: 4.9 | H100: Indicador de investimento por aluno | I100: 4.9 - Investimento educacional por aluno | J100: 5895.48
A101: =C101&D101&G101 -> Frei Gaspar20151.1 | B101: 3126802 | C101: Frei Gaspar | D101: 2015 | E101: 1 | F101: 24 | G101: 1.1 | H101: Indicador legal | I101: 1.1 - Percentual de aplicação das receitas de impostos e transferências vinculadas à educação em MDE (mínimo de 25% para estados, DF e municípios) | J101: 0.2504
A102: =C102&D102&G102 -> Frei Gaspar20151.2 | B102: 3126802 | C102: Frei Gaspar | D102: 2015 | E102: 1 | F102: 67 | G102: 1.2 | H102: Indicador legal | I102: 1.2 - Percentual de aplicação do FUNDEB na remuneração dos profissionais da educação (mínimo de 70%) - Inciso XXII, Portaria Conjunta MGI/MF/CGU Nº 33 de30-08-2023 | J102: 0.9168
... A117: =C117&D117&G117 -> Fronteira dos Vales20151.3 | B117: 3127057 | C117: Fronteira dos Vales | D117: 2015 | E117: 1 | F117: 68 | G117: 1.3 | H117: Indicador legal | I117: 1.3 - Percentual de aplicação do FUNDEB em despesas com MDE, que não remuneração dos profissionais da educação (máximo de 30%) | J117: 0.1745
A118: =C118&D118&G118 -> Fronteira dos Vales20152.1 | B118: 3127057 | C118: Fronteira dos Vales | D118: 2015 | E118: 1 | F118: 28 | G118: 2.1 | H118: Indicador de dispêndio financeiro | I118: 2.1 - Percentual dos recursos do FUNDEB aplicados na educação infantil
A119: =C119&D119&G119 -> Fronteira dos Vales20152.2 | B119: 3127057 | C119: Fronteira dos Vales | D119: 2015 | E119: 1 | F119: 29 | G119: 2.2 | H119: Indicador de dispêndio financeiro | I119: 2.2 - Percentual dos recursos do FUNDEB aplicados no ensino fundamental | J119: 0.9488
A120: =C120&D120&G120 -> Fronteira dos Vales20152.4 | B120: 3127057 | C120: Fronteira dos Vales | D120: 2015 | E120: 1 | F120: 31 | G120: 2.4 | H120: Indicador de dispêndio financeiro | I120: 2.4 - Percentual das despesas com educação infantil em relação à despesa total com educação | J120: 0.0617
A121: =C121&D121&G121 -> Fronteira dos Vales20152.5 | B121: 3127057 | C121: Fronteira dos Vales | D121: 2015 | E121: 1 | F121: 32 | G121: 2.5 | H121: Indicador de dispêndio financeiro | I121: 2.5 - Percentual das despesas com ensino fundamental em relação à despesa total com educação | J121: 0.8607
A122: =C122&D122&G122 -> Fronteira dos Vales20152.8 | B122: 3127057 | C122: Fronteira dos Vales | D122: 2015 | E122: 1 | F122: 35 | G122: 2.8 | H122: Indicador de dispêndio financeiro | I122: 2.8 - Percentual das despesas em educação em relação às despesas de todas as áreas | J122: 0.2902
A123: =C123&D123&G123 -> Fronteira dos Vales20154.1 | B123: 3127057 | C123: Fronteira dos Vales | D123: 2015 | E123: 1 | F123: 44 | G123: 4.1 | H123: Indicador de investimento por aluno | I123: 4.1 - Investimento educacional por aluno da educação infantil | J123: 1800.03
A124: =C124&D124&G124 -> Fronteira dos Vales20154.10 | B124: 3127057 | C124: Fronteira dos Vales | D124: 2015 | E124: 1 | F124: 58 | G124: 4.10 | H124: Indicador de investimento por aluno | I124: 4.10 - Despesa com professores por aluno da educação básica | J124: 2216.65
A125: =C125&D125&G125 -> Fronteira dos Vales20154.11 | B125: 3127057 | C125: Fronteira dos Vales | D125: 2015 | E125: 1 | F125: 59 | G125: 4.11 | H125: Indicador de investimento por aluno | I125: 4.11 - Despesas com profissionais não docentes da área educacional por aluno da educação básica | J125: 2862.24
A126: =C126&D126&G126 -> Fronteira dos Vales20154.2 | B126: 3127057 | C126: Fronteira dos Vales | D126: 2015 | E126: 1 | F126: 45 | G126: 4.2 | H126: Indicador de investimento por aluno | I126: 4.2 - Investimento educacional por aluno do ensino fundamental | J126: 8410.91
A127: =C127&D127&G127 -> Fronteira dos Vales20154.8 | B127: 3127057 | C127: Fronteira dos Vales | D127: 2015 | E127: 1 | F127: 56 | G127: 4.8 | H127: Indicador de investimento por aluno | I127: 4.8 - Investimento educacional por aluno da educação básica | J127: 6369.41
A128: =C128&D128&G128 -> Fronteira dos Vales20154.9 | B128: 3127057 | C128: Fronteira dos Vales | D128: 2015 | E128: 1 | F128: 57 | G128: 4.9 | H128: Indicador de investimento por aluno | I128: 4.9 - Investimento educacional por aluno | J128: 6369.41
A129: =C129&D129&G129 -> Itaipé20151.1 | B129: 3132305 | C129: Itaipé | D129: 2015 | E129: 1 | F129: 24 | G129: 1.1 | H129: Indicador legal | I129: 1.1 - Percentual de aplicação das receitas de impostos e transferências vinculadas à educação em MDE (mínimo de 25% para estados, DF e municípios) | J129: 0.2524
A130: =C130&D130&G130 -> Itaipé20151.2 | B130: 3132305 | C130: Itaipé | D130: 2015 | E130: 1 | F130: 67 | G130: 1.2 | H130: Indicador legal | I130: 1.2 - Percentual de aplicação do FUNDEB na remuneração dos profissionais da educação (mínimo de 70%) - Inciso XXII, Portaria Conjunta MGI/MF/CGU Nº 33 de30-08-2023 | J130: 0.6042
... A257: =C257&D257&G257 -> Santa Helena de Minas20151.3 | B257: 3157658 | C257: Santa Helena de Minas | D257: 2015 | E257: 1 | F257: 68 | G257: 1.3 | H257: Indicador legal | I257: 1.3 - Percentual de aplicação do FUNDEB em despesas com MDE, que não remuneração dos profissionais da educação (máximo de 30%) | J257: 0.1013
A258: =C258&D258&G258 -> Santa Helena de Minas20152.1 | B258: 3157658 | C258: Santa Helena de Minas | D258: 2015 | E258: 1 | F258: 28 | G258: 2.1 | H258: Indicador de dispêndio financeiro | I258: 2.1 - Percentual dos recursos do FUNDEB aplicados na educação infantil
A259: =C259&D259&G259 -> Santa Helena de Minas20152.2 | B259: 3157658 | C259: Santa Helena de Minas | D259: 2015 | E259: 1 | F259: 29 | G259: 2.2 | H259: Indicador de dispêndio financeiro | I259: 2.2 - Percentual dos recursos do FUNDEB aplicados no ensino fundamental | J259: 0.8565
A260: =C260&D260&G260 -> Santa Helena de Minas20152.4 | B260: 3157658 | C260: Santa Helena de Minas | D260: 2015 | E260: 1 | F260: 31 | G260: 2.4 | H260: Indicador de dispêndio financeiro | I260: 2.4 - Percentual das despesas com educação infantil em relação à despesa total com educação | J260: 0.0792
A261: =C261&D261&G261 -> Santa Helena de Minas20152.5 | B261: 3157658 | C261: Santa Helena de Minas | D261: 2015 | E261: 1 | F261: 32 | G261: 2.5 | H261: Indicador de dispêndio financeiro | I261: 2.5 - Percentual das despesas com ensino fundamental em relação à despesa total com educação | J261: 0.8412
A262: =C262&D262&G262 -> Santa Helena de Minas20152.8 | B262: 3157658 | C262: Santa Helena de Minas | D262: 2015 | E262: 1 | F262: 35 | G262: 2.8 | H262: Indicador de dispêndio financeiro | I262: 2.8 - Percentual das despesas em educação em relação às despesas de todas as áreas | J262: 0.1987
A263: =C263&D263&G263 -> Santa Helena de Minas20154.1 | B263: 3157658 | C263: Santa Helena de Minas | D263: 2015 | E263: 1 | F263: 44 | G263: 4.1 | H263: Indicador de investimento por aluno | I263: 4.1 - Investimento educacional por aluno da educação infantil | J263: 2240.44
A264: =C264&D264&G264 -> Santa Helena de Minas20154.10 | B264: 3157658 | C264: Santa Helena de Minas | D264: 2015 | E264: 1 | F264: 58 | G264: 4.10 | H264: Indicador de investimento por aluno | I264: 4.10 - Despesa com professores por aluno da educação básica | J264: 2816.61
A265: =C265&D265&G265 -> Santa Helena de Minas20154.11 | B265: 3157658 | C265: Santa Helena de Minas | D265: 2015 | E265: 1 | F265: 59 | G265: 4.11 | H265: Indicador de investimento por aluno | I265: 4.11 - Despesas com profissionais não docentes da área educacional por aluno da educação básica | J265: 284.58
A266: =C266&D266&G266 -> Santa Helena de Minas20154.2 | B266: 3157658 | C266: Santa Helena de Minas | D266: 2015 | E266: 1 | F266: 45 | G266: 4.2 | H266: Indicador de investimento por aluno | I266: 4.2 - Investimento educacional por aluno do ensino fundamental | J266: 5787.97
A267: =C267&D267&G267 -> Santa Helena de Minas20154.8 | B267: 3157658 | C267: Santa Helena de Minas | D267: 2015 | E267: 1 | F267: 56 | G267: 4.8 | H267: Indicador de investimento por aluno | I267: 4.8 - Investimento educacional por aluno da educação básica | J267: 5093.35
A268: =C268&D268&G268 -> Santa Helena de Minas20154.9 | B268: 3157658 | C268: Santa Helena de Minas | D268: 2015 | E268: 1 | F268: 57 | G268: 4.9 | H268: Indicador de investimento por aluno | I268: 4.9 - Investimento educacional por aluno | J268: 5093.35
A269: =C269&D269&G269 -> Serra dos Aimorés20151.1 | B269: 3166709 | C269: Serra dos Aimorés | D269: 2015 | E269: 1 | F269: 24 | G269: 1.1 | H269: Indicador legal | I269: 1.1 - Percentual de aplicação das receitas de impostos e transferências vinculadas à educação em MDE (mínimo de 25% para estados, DF e municípios) | J269: 0.2543
A270: =C270&D270&G270 -> Serra dos Aimorés20151.2 | B270: 3166709 | C270: Serra dos Aimorés | D270: 2015 | E270: 1 | F270: 67 | G270: 1.2 | H270: Indicador legal | I270: 1.2 - Percentual de aplicação do FUNDEB na remuneração dos profissionais da educação (mínimo de 70%) - Inciso XXII, Portaria Conjunta MGI/MF/CGU Nº 33 de30-08-2023 | J270: 0.9693
... A278: =C278&D278&G278 -> Serra dos Aimorés20154.10 | B278: 3166709 | C278: Serra dos Aimorés | D278: 2015 | E278: 1 | F278: 58 | G278: 4.10 | H278: Indicador de investimento por aluno | I278: 4.10 - Despesa com professores por aluno da educação básica | J278: 3830.94
A279: =C279&D279&G279 -> Serra dos Aimorés20154.11 | B279: 3166709 | C279: Serra dos Aimorés | D279: 2015 | E279: 1 | F279: 59 | G279: 4.11 | H279: Indicador de investimento por aluno | I279: 4.11 - Despesas com profissionais não docentes da área educacional por aluno da educação básica
A280: =C280&D280&G280 -> Serra dos Aimorés20154.2 | B280: 3166709 | C280: Serra dos Aimorés | D280: 2015 | E280: 1 | F280: 45 | G280: 4.2 | H280: Indicador de investimento por aluno | I280: 4.2 - Investimento educacional por aluno do ensino fundamental | J280: 6246.53
A281: =C281&D281&G281 -> Serra dos Aimorés20154.8 | B281: 3166709 | C281: Serra dos Aimorés | D281: 2015 | E281: 1 | F281: 56 | G281: 4.8 | H281: Indicador de investimento por aluno | I281: 4.8 - Investimento educacional por aluno da educação básica | J281: 4446.88
A282: =C282&D282&G282 -> Serra dos Aimorés20154.9 | B282: 3166709 | C282: Serra dos Aimorés | D282: 2015 | E282: 1 | F282: 57 | G282: 4.9 | H282: Indicador de investimento por aluno | I282: 4.9 - Investimento educacional por aluno | J282: 4446.88
A283: =C283&D283&G283 -> Setubinha20151.1 | B283: 3165552 | C283: Setubinha | D283: 2015 | E283: 1 | F283: 24 | G283: 1.1 | H283: Indicador legal | I283: 1.1 - Percentual de aplicação das receitas de impostos e transferências vinculadas à educação em MDE (mínimo de 25% para estados, DF e municípios) | J283: 0.2522
A284: =C284&D284&G284 -> Setubinha20151.2 | B284: 3165552 | C284: Setubinha | D284: 2015 | E284: 1 | F284: 67 | G284: 1.2 | H284: Indicador legal | I284: 1.2 - Percentual de aplicação do FUNDEB na remuneração dos profissionais da educação (mínimo de 70%) - Inciso XXII, Portaria Conjunta MGI/MF/CGU Nº 33 de30-08-2023 | J284: 0.7711
A285: =C285&D285&G285 -> Setubinha20151.3 | B285: 3165552 | C285: Setubinha | D285: 2015 | E285: 1 | F285: 68 | G285: 1.3 | H285: Indicador legal | I285: 1.3 - Percentual de aplicação do FUNDEB em despesas com MDE, que não remuneração dos profissionais da educação (máximo de 30%) | J285: 0.2289
A286: =C286&D286&G286 -> Setubinha20152.1 | B286: 3165552 | C286: Setubinha | D286: 2015 | E286: 1 | F286: 28 | G286: 2.1 | H286: Indicador de dispêndio financeiro | I286: 2.1 - Percentual dos recursos do FUNDEB aplicados na educação infantil | J286: 0.0288
A287: =C287&D287&G287 -> Setubinha20152.2 | B287: 3165552 | C287: Setubinha | D287: 2015 | E287: 1 | F287: 29 | G287: 2.2 | H287: Indicador de dispêndio financeiro | I287: 2.2 - Percentual dos recursos do FUNDEB aplicados no ensino fundamental | J287: 0.8148
A288: =C288&D288&G288 -> Setubinha20152.4 | B288: 3165552 | C288: Setubinha | D288: 2015 | E288: 1 | F288: 31 | G288: 2.4 | H288: Indicador de dispêndio financeiro | I288: 2.4 - Percentual das despesas com educação infantil em relação à despesa total com educação | J288: 0.0965
A289: =C289&D289&G289 -> Setubinha20152.5 | B289: 3165552 | C289: Setubinha | D289: 2015 | E289: 1 | F289: 32 | G289: 2.5 | H289: Indicador de dispêndio financeiro | I289: 2.5 - Percentual das despesas com ensino fundamental em relação à despesa total com educação | J289: 0.8565
A290: =C290&D290&G290 -> Setubinha20152.8 | B290: 3165552 | C290: Setubinha | D290: 2015 | E290: 1 | F290: 35 | G290: 2.8 | H290: Indicador de dispêndio financeiro | I290: 2.8 - Percentual das despesas em educação em relação às despesas de todas as áreas | J290: 0.3077
A291: =C291&D291&G291 -> Setubinha20154.1 | B291: 3165552 | C291: Setubinha | D291: 2015 | E291: 1 | F291: 44 | G291: 4.1 | H291: Indicador de investimento por aluno | I291: 4.1 - Investimento educacional por aluno da educação infantil | J291: 2149.51
... A340: =C340&D340&G340 -> Ataléia20161.2 | B340: 3104700 | C340: Ataléia | D340: 2016 | E340: 1 | F340: 67 | G340: 1.2 | H340: Indicador legal | I340: 1.2 - Percentual de aplicação do FUNDEB na remuneração dos profissionais da educação (mínimo de 70%) - Inciso XXII, Portaria Conjunta MGI/MF/CGU Nº 33 de30-08-2023 | J340: 1
A341: =C341&D341&G341 -> Ataléia20161.3 | B341: 3104700 | C341: Ataléia | D341: 2016 | E341: 1 | F341: 68 | G341: 1.3 | H341: Indicador legal | I341: 1.3 - Percentual de aplicação do FUNDEB em despesas com MDE, que não remuneração dos profissionais da educação (máximo de 30%)
A342: =C342&D342&G342 -> Ataléia20162.1 | B342: 3104700 | C342: Ataléia | D342: 2016 | E342: 1 | F342: 28 | G342: 2.1 | H342: Indicador de dispêndio financeiro | I342: 2.1 - Percentual dos recursos do FUNDEB aplicados na educação infantil | J342: 0.0697
A343: =C343&D343&G343 -> Ataléia20162.2 | B343: 3104700 | C343: Ataléia | D343: 2016 | E343: 1 | F343: 29 | G343: 2.2 | H343: Indicador de dispêndio financeiro | I343: 2.2 - Percentual dos recursos do FUNDEB aplicados no ensino fundamental | J343: 0.7723
A344: =C344&D344&G344 -> Ataléia20162.4 | B344: 3104700 | C344: Ataléia | D344: 2016 | E344: 1 | F344: 31 | G344: 2.4 | H344: Indicador de dispêndio financeiro | I344: 2.4 - Percentual das despesas com educação infantil em relação à despesa total com educação | J344: 0.2133
A345: =C345&D345&G345 -> Ataléia20162.5 | B345: 3104700 | C345: Ataléia | D345: 2016 | E345: 1 | F345: 32 | G345: 2.5 | H345: Indicador de dispêndio financeiro | I345: 2.5 - Percentual das despesas com ensino fundamental em relação à despesa total com educação | J345: 0.6878
A346: =C346&D346&G346 -> Ataléia20162.8 | B346: 3104700 | C346: Ataléia | D346: 2016 | E346: 1 | F346: 35 | G346: 2.8 | H346: Indicador de dispêndio financeiro | I346: 2.8 - Percentual das despesas em educação em relação às despesas de todas as áreas | J346: 0.317
A347: =C347&D347&G347 -> Ataléia20164.1 | B347: 3104700 | C347: Ataléia | D347: 2016 | E347: 1 | F347: 44 | G347: 4.1 | H347: Indicador de investimento por aluno | I347: 4.1 - Investimento educacional por aluno da educação infantil | J347: 4538.15
A348: =C348&D348&G348 -> Ataléia20164.10 | B348: 3104700 | C348: Ataléia | D348: 2016 | E348: 1 | F348: 58 | G348: 4.10 | H348: Indicador de investimento por aluno | I348: 4.10 - Despesa com professores por aluno da educação básica | J348: 5225.27
A349: =C349&D349&G349 -> Ataléia20164.11 | B349: 3104700 | C349: Ataléia | D349: 2016 | E349: 1 | F349: 59 | G349: 4.11 | H349: Indicador de investimento por aluno | I349: 4.11 - Despesas com profissionais não docentes da área educacional por aluno da educação básica | J349: 1839.72
A350: =C350&D350&G350 -> Ataléia20164.2 | B350: 3104700 | C350: Ataléia | D350: 2016 | E350: 1 | F350: 45 | G350: 4.2 | H350: Indicador de investimento por aluno | I350: 4.2 - Investimento educacional por aluno do ensino fundamental | J350: 10166.3
A351: =C351&D351&G351 -> Ataléia20164.8 | B351: 3104700 | C351: Ataléia | D351: 2016 | E351: 1 | F351: 56 | G351: 4.8 | H351: Indicador de investimento por aluno | I351: 4.8 - Investimento educacional por aluno da educação básica | J351: 7450.74
A352: =C352&D352&G352 -> Ataléia20164.9 | B352: 3104700 | C352: Ataléia | D352: 2016 | E352: 1 | F352: 57 | G352: 4.9 | H352: Indicador de investimento por aluno | I352: 4.9 - Investimento educacional por aluno | J352: 7450.74
A353: =C353&D353&G353 -> Bertópolis20161.1 | B353: 3106606 | C353: Bertópolis | D353: 2016 | E353: 1 | F353: 24 | G353: 1.1 | H353: Indicador legal | I353: 1.1 - Percentual de aplicação das receitas de impostos e transferências vinculadas à educação em MDE (mínimo de 25% para estados, DF e municípios) | J353: 0.2556
... A355: =C355&D355&G355 -> Bertópolis20161.3 | B355: 3106606 | C355: Bertópolis | D355: 2016 | E355: 1 | F355: 68 | G355: 1.3 | H355: Indicador legal | I355: 1.3 - Percentual de aplicação do FUNDEB em despesas com MDE, que não remuneração dos profissionais da educação (máximo de 30%) | J355: 0.0614
A356: =C356&D356&G356 -> Bertópolis20162.1 | B356: 3106606 | C356: Bertópolis | D356: 2016 | E356: 1 | F356: 28 | G356: 2.1 | H356: Indicador de dispêndio financeiro | I356: 2.1 - Percentual dos recursos do FUNDEB aplicados na educação infantil
...

Sheet INTEGRALIDADE
B1: 1.1 | C1: 1.1 | D1: 1.1 | E1: 1.1 | F1: 1.1 | G1: 1.1 | H1: 1.1 | I1: 1.1 | J1: 1.1 | K1: 1.1 | L1: 1.2 | M1: 1.2 | N1: 1.2 | O1: 1.2 | P1: 1.2 | Q1: 1.2 | R1: 1.2 | S1: 1.2 | T1: 1.2 | U1: 1.2 | V1: 1.3 | W1: 1.3 | X1: 1.3 | Y1: 1.3 | Z1: 1.3 | AA1: 1.3 | AB1: 1.3 | AC1: 1.3 | AD1: 1.3 | AE1: 1.3 | AF1: 2.1 | AG1: 2.1 | AH1: 2.1 | AI1: 2.1 | AJ1: 2.1 | AK1: 2.1 | AL1: 2.1 | AM1: 2.1 | AN1: 2.1 | AO1: 2.1 | AP1: 2.2 | AQ1: 2.2 | AR1: 2.2 | AS1: 2.2 | AT1: 2.2 | AU1: 2.2 | AV1: 2.2 | AW1: 2.2 | AX1: 2.2 | AY1: 2.2 | AZ1: 2.4 | BA1: 2.4 | BB1: 2.4 | BC1: 2.4 | BD1: 2.4 | BE1: 2.4 | BF1: 2.4 | BG1: 2.4 | BH1: 2.4 | BI1: 2.4 | BJ1: 2.5 | BK1: 2.5 | BL1: 2.5 | BM1: 2.5 | BN1: 2.5 | BO1: 2.5 | BP1: 2.5 | BQ1: 2.5 | BR1: 2.5 | BS1: 2.5 | BT1: 2.8 | BU1: 2.8 | BV1: 2.8 | BW1: 2.8 | BX1: 2.8 | BY1: 2.8 | BZ1: 2.8 | CA1: 2.8 | CB1: 2.8 | CC1: 2.8 | CD1: 4.1 | CE1: 4.1 | CF1: 4.1 | CG1: 4.1 | CH1: 4.1 | CI1: 4.1 | CJ1: 4.1 | CK1: 4.1 | CL1: 4.1 | CM1: 4.1 | CN1: 4.2 | CO1: 4.2 | CP1: 4.2 | CQ1: 4.2 | CR1: 4.2 | CS1: 4.2 | CT1: 4.2 | CU1: 4.2 | CV1: 4.2 | CW1: 4.2 | CX1: 4.8 | CY1: 4.8 | CZ1: 4.8 | DA1: 4.8 | DB1: 4.8 | DC1: 4.8 | DD1: 4.8 | DE1: 4.8 | DF1: 4.8 | DG1: 4.8 | DH1: 4.9 | DI1: 4.9 | DJ1: 4.9 | DK1: 4.9 | DL1: 4.9 | DM1: 4.9 | DN1: 4.9 | DO1: 4.9 | DP1: 4.9 | DQ1: 4.9 | DR1: 4.10 | DS1: 4.10 | DT1: 4.10 | DU1: 4.10 | DV1: 4.10 | DW1: 4.10 | DX1: 4.10 | DY1: 4.10 | DZ1: 4.10 | EA1: 4.10 | EB1: 4.11 | EC1: 4.11 | ED1: 4.11 | EE1: 4.11 | EF1: 4.11 | EG1: 4.11 | EH1: 4.11 | EI1: 4.11 | EJ1: 4.11 | EK1: 4.11
B2: 1.1 - Percentual de aplicação das receitas de impostos e transferências vinculadas à educação em MDE (mínimo de 25% para estados, DF e municípios) | L2: 1.2 - Percentual de aplicação do FUNDEB na remuneração dos profissionais da educação (mínimo de 70%) - Inciso XXII, Portaria Conjunta MGI/MF/CGU Nº 33 de30-08-2023 | V2: 1.3 - Percentual de aplicação do FUNDEB em despesas com MDE, que não remuneração dos profissionais da educação (máximo de 30%) | AF2: 2.1 - Percentual dos recursos do FUNDEB aplicados na educação infantil | AP2: 2.2 - Percentual dos recursos do FUNDEB aplicados no ensino fundamental | AZ2: 2.4 - Percentual das despesas com educação infantil em relação à despesa total com educação | BJ2: 2.5 - Percentual das despesas com ensino fundamental em relação à despesa total com educação | BT2: 2.8 - Percentual das despesas em educação em relação às despesas de todas as áreas | CD2: 4.1 - Investimento educacional por aluno da educação infantil | CN2: 4.2 - Investimento educacional por aluno do ensino fundamental | CX2: 4.8 - Investimento educacional por aluno da educação básica | DH2: 4.9 - Investimento educacional por aluno | DR2: 4.10 - Despesa com professores por aluno da educação básica | EB2: 4.11 - Despesas com profissionais não docentes da área educacional por aluno da educação básica
A3: CIDADE | B3: 2015 | C3: 2016 | D3: 2017 | E3: 2018 | F3: 2019 | G3: 2020 | H3: 2021 | I3: 2022 | J3: 2023 | K3: 2024 | L3: 2015 | M3: 2016 | N3: 2017 | O3: 2018 | P3: 2019 | Q3: 2020 | R3: 2021 | S3: 2022 | T3: 2023 | U3: 2024 | V3: 2015 | W3: 2016 | X3: 2017 | Y3: 2018 | Z3: 2019 | AA3: 2020 | AB3: 2021 | AC3: 2022 | AD3: 2023 | AE3: 2024 | AF3: 2015 | AG3: 2016 | AH3: 2017 | AI3: 2018 | AJ3: 2019 | AK3: 2020 | AL3: 2021 | AM3: 2022 | AN3: 2023 | AO3: 2024 | AP3: 2015 | AQ3: 2016 | AR3: 2017 | AS3: 2018 | AT3: 2019 | AU3: 2020 | AV3: 2021 | AW3: 2022 | AX3: 2023 | AY3: 2024 | AZ3: 2015 | BA3: 2016 | BB3: 2017 | BC3: 2018 | BD3: 2019 | BE3: 2020 | BF3: 2021 | BG3: 2022 | BH3: 2023 | BI3: 2024 | BJ3: 2015 | BK3: 2016 | BL3: 2017 | BM3: 2018 | BN3: 2019 | BO3: 2020 | BP3: 2021 | BQ3: 2022 | BR3: 2023 | BS3: 2024 | BT3: 2015 | BU3: 2016 | BV3: 2017 | BW3: 2018 | BX3: 2019 | BY3: 2020 | BZ3: 2021 | CA3: 2022 | CB3: 2023 | CC3: 2024 | CD3: 2015 | CE3: 2016 | CF3: 2017 | CG3: 2018 | CH3: 2019 | CI3: 2020 | CJ3: 2021 | CK3: 2022 | CL3: 2023 | CM3: 2024 | CN3: 2015 | CO3: 2016 | CP3: 2017 | CQ3: 2018 | CR3: 2019 | CS3: 2020 | CT3: 2021 | CU3: 2022 | CV3: 2023 | CW3: 2024 | CX3: 2015 | CY3: 2016 | CZ3: 2017 | DA3: 2018 | DB3: 2019 | DC3: 2020 | DD3: 2021 | DE3: 2022 | DF3: 2023 | DG3: 2024 | DH3: 2015 | DI3: 2016 | DJ3: 2017 | DK3: 2018 | DL3: 2019 | DM3: 2020 | DN3: 2021 | DO3: 2022 | DP3: 2023 | DQ3: 2024 | DR3: 2015 | DS3: 2016 | DT3: 2017 | DU3: 2018 | DV3: 2019 | DW3: 2020 | DX3: 2021 | DY3: 2022 | DZ3: 2023 | EA3: 2024 | EB3: 2015 | EC3: 2016 | ED3: 2017 | EE3: 2018 | EF3: 2019 | EG3: 2020 | EH3: 2021 | EI3: 2022 | EJ3: 2023 | EK3: 2024
A4: Águas Formosas | B4: =VLOOKUP($A4&B$3&B$1,DB!$A:$J,10,0) -> 0.282 | C4: =VLOOKUP($A4&C$3&C$1,DB!$A:$J,10,0) -> 0.2579 | D4: =VLOOKUP($A4&D$3&D$1,DB!$A:$J,10,0) -> 0.2814 | E4: =VLOOKUP($A4&E$3&E$1,DB!$A:$J,10,0) -> 0.2965 | F4: =VLOOKUP($A4&F$3&F$1,DB!$A:$J,10,0) -> 0.2877 | G4: =VLOOKUP($A4&G$3&G$1,DB!$A:$J,10,0) -> 0.2906 | H4: =VLOOKUP($A4&H$3&H$1,DB!$A:$J,10,0) -> 0.2092 | I4: =VLOOKUP($A4&I$3&I$1,DB!$A:$J,10,0) -> 0.261 | ... EK4: =VLOOKUP($A4&EK$3&EK$1,DB!$A:$J,10,0) -> 130.72
A5: Ataléia | B5: =VLOOKUP($A5&B$3&B$1,DB!$A:$J,10,0) -> 0.308 | C5: =VLOOKUP($A5&C$3&C$1,DB!$A:$J,10,0) -> 0.2876 | D5: =VLOOKUP($A5&D$3&D$1,DB!$A:$J,10,0) -> 0.2521 | E5: =VLOOKUP($A5&E$3&E$1,DB!$A:$J,10,0) -> 0.3451 | F5: =VLOOKUP($A5&F$3&F$1,DB!$A:$J,10,0) -> 0.2892 | G5: =VLOOKUP($A5&G$3&G$1,DB!$A:$J,10,0) -> 0.315 | H5: =VLOOKUP($A5&H$3&H$1,DB!$A:$J,10,0) -> 0.2389 | I5: =VLOOKUP($A5&I$3&I$1,DB!$A:$J,10,0) -> 0.2506 | ... EK5: =VLOOKUP($A5&EK$3&EK$1,DB!$A:$J,10,0) -> 44.7
A6: Bertópolis | B6: =VLOOKUP($A6&B$3&B$1,DB!$A:$J,10,0) -> 0.3032 | C6: =VLOOKUP($A6&C$3&C$1,DB!$A:$J,10,0) -> 0.2556 | D6: =VLOOKUP($A6&D$3&D$1,DB!$A:$J,10,0) -> 0.3447 | E6: =VLOOKUP($A6&E$3&E$1,DB!$A:$J,10,0) -> 0.2859 | F6: =VLOOKUP($A6&F$3&F$1,DB!$A:$J,10,0) -> 0.2701 | G6: =VLOOKUP($A6&G$3&G$1,DB!$A:$J,10,0) -> 0.2504 | H6: =VLOOKUP($A6&H$3&H$1,DB!$A:$J,10,0) -> 0.2065 | I6: =VLOOKUP($A6&I$3&I$1,DB!$A:$J,10,0) -> 0.2587 | ... EK6: =VLOOKUP($A6&EK$3&EK$1,DB!$A:$J,10,0) -> #N/A
A7: Carlos Chagas | B7: =VLOOKUP($A7&B$3&B$1,DB!$A:$J,10,0) -> 0.3021 | C7: =VLOOKUP($A7&C$3&C$1,DB!$A:$J,10,0) -> 0.3038 | D7: =VLOOKUP($A7&D$3&D$1,DB!$A:$J,10,0) -> 0.2969 | E7: =VLOOKUP($A7&E$3&E$1,DB!$A:$J,10,0) -> 0.3309 | F7: =VLOOKUP($A7&F$3&F$1,DB!$A:$J,10,0) -> 0.258 | G7: =VLOOKUP($A7&G$3&G$1,DB!$A:$J,10,0) -> 0.2435 | H7: =VLOOKUP($A7&H$3&H$1,DB!$A:$J,10,0) -> 0.2553 | I7: =VLOOKUP($A7&I$3&I$1,DB!$A:$J,10,0) -> 0.26 | ... EK7: =VLOOKUP($A7&EK$3&EK$1,DB!$A:$J,10,0) -> 519.81
A8: Catuji | B8: =VLOOKUP($A8&B$3&B$1,DB!$A:$J,10,0) -> 0.2571 | C8: =VLOOKUP($A8&C$3&C$1,DB!$A:$J,10,0) -> 0.2948 | D8: =VLOOKUP($A8&D$3&D$1,DB!$A:$J,10,0) -> 0.2632 | E8: =VLOOKUP($A8&E$3&E$1,DB!$A:$J,10,0) -> 0.2972 | F8: =VLOOKUP($A8&F$3&F$1,DB!$A:$J,10,0) -> 0.3544 | G8: =VLOOKUP($A8&G$3&G$1,DB!$A:$J,10,0) -> 0.2812 | H8: =VLOOKUP($A8&H$3&H$1,DB!$A:$J,10,0) -> 0.265 | I8: =VLOOKUP($A8&I$3&I$1,DB!$A:$J,10,0) -> 0.2731 | ... EK8: =VLOOKUP($A8&EK$3&EK$1,DB!$A:$J,10,0) -> 1498.24
A9: Crisólita | B9: =VLOOKUP($A9&B$3&B$1,DB!$A:$J,10,0) -> 0.2558 | C9: =VLOOKUP($A9&C$3&C$1,DB!$A:$J,10,0) -> 0.2993 | D9: =VLOOKUP($A9&D$3&D$1,DB!$A:$J,10,0) -> 0.2521 | E9: =VLOOKUP($A9&E$3&E$1,DB!$A:$J,10,0) -> 0.2554 | F9: =VLOOKUP($A9&F$3&F$1,DB!$A:$J,10,0) -> 0.2574 | G9: =VLOOKUP($A9&G$3&G$1,DB!$A:$J,10,0) -> 0.2582 | H9: =VLOOKUP($A9&H$3&H$1,DB!$A:$J,10,0) -> 0.256 | I9: =VLOOKUP($A9&I$3&I$1,DB!$A:$J,10,0) -> 0.2568 | ... EK9: =VLOOKUP($A9&EK$3&EK$1,DB!$A:$J,10,0) -> 1302.79
A10: Franciscópolis | B10: =VLOOKUP($A10&B$3&B$1,DB!$A:$J,10,0) -> 0.3083 | C10: =VLOOKUP($A10&C$3&C$1,DB!$A:$J,10,0) -> 0.2581 | D10: =VLOOKUP($A10&D$3&D$1,DB!$A:$J,10,0) -> 0.3273 | E10: =VLOOKUP($A10&E$3&E$1,DB!$A:$J,10,0) -> 0.3058 | F10: =VLOOKUP($A10&F$3&F$1,DB!$A:$J,10,0) -> 0.3288 | G10: =VLOOKUP($A10&G$3&G$1,DB!$A:$J,10,0) -> 0.2967 | H10: =VLOOKUP($A10&H$3&H$1,DB!$A:$J,10,0) -> 0.258 | I10: =VLOOKUP($A10&I$3&I$1,DB!$A:$J,10,0) -> 0.2842 | ... EK10: =VLOOKUP($A10&EK$3&EK$1,DB!$A:$J,10,0) -> 0
A11: Frei Gaspar | B11: =VLOOKUP($A11&B$3&B$1,DB!$A:$J,10,0) -> 0.2504 | C11: =VLOOKUP($A11&C$3&C$1,DB!$A:$J,10,0) -> 0.2877 | D11: =VLOOKUP($A11&D$3&D$1,DB!$A:$J,10,0) -> 0.3127 | E11: =VLOOKUP($A11&E$3&E$1,DB!$A:$J,10,0) -> 0.259 | F11: =VLOOKUP($A11&F$3&F$1,DB!$A:$J,10,0) -> 0.3349 | G11: =VLOOKUP($A11&G$3&G$1,DB!$A:$J,10,0) -> 0.2983 | H11: =VLOOKUP($A11&H$3&H$1,DB!$A:$J,10,0) -> 0.2732 | I11: =VLOOKUP($A11&I$3&I$1,DB!$A:$J,10,0) -> 0.3183 | ... EK11: =VLOOKUP($A11&EK$3&EK$1,DB!$A:$J,10,0) -> 1137.38
A12: Fronteira dos Vales | B12: =VLOOKUP($A12&B$3&B$1,DB!$A:$J,10,0) -> 0.32 | C12: =VLOOKUP($A12&C$3&C$1,DB!$A:$J,10,0) -> 0.3124 | D12: =VLOOKUP($A12&D$3&D$1,DB!$A:$J,10,0) -> 0.2609 | E12: =VLOOKUP($A12&E$3&E$1,DB!$A:$J,10,0) -> 0.2918 | F12: =VLOOKUP($A12&F$3&F$1,DB!$A:$J,10,0) -> 0.2875 | G12: =VLOOKUP($A12&G$3&G$1,DB!$A:$J,10,0) -> 0.2892 | H12: =VLOOKUP($A12&H$3&H$1,DB!$A:$J,10,0) -> 0.2466 | I12: =VLOOKUP($A12&I$3&I$1,DB!$A:$J,10,0) -> 0.275 | ... EK12: =VLOOKUP($A12&EK$3&EK$1,DB!$A:$J,10,0) -> 541.14
A13: Itaipé | B13: =VLOOKUP($A13&B$3&B$1,DB!$A:$J,10,0) -> 0.2524 | C13: =VLOOKUP($A13&C$3&C$1,DB!$A:$J,10,0) -> 0.2671 | D13: =VLOOKUP($A13&D$3&D$1,DB!$A:$J,10,0) -> 0.2896 | E13: =VLOOKUP($A13&E$3&E$1,DB!$A:$J,10,0) -> 0.251 | F13: =VLOOKUP($A13&F$3&F$1,DB!$A:$J,10,0) -> 0.2974 | G13: =VLOOKUP($A13&G$3&G$1,DB!$A:$J,10,0) -> 0.2566 | H13: =VLOOKUP($A13&H$3&H$1,DB!$A:$J,10,0) -> 0.2439 | I13: =VLOOKUP($A13&I$3&I$1,DB!$A:$J,10,0) -> 0.265 | ... EK13: =VLOOKUP($A13&EK$3&EK$1,DB!$A:$J,10,0) -> 0
A14: Ladainha | B14: =VLOOKUP($A14&B$3&B$1,DB!$A:$J,10,0) -> 0.2514 | C14: =VLOOKUP($A14&C$3&C$1,DB!$A:$J,10,0) -> 0.2872 | D14: =VLOOKUP($A14&D$3&D$1,DB!$A:$J,10,0) -> 0.2704 | E14: =VLOOKUP($A14&E$3&E$1,DB!$A:$J,10,0) -> 0.2779 | F14: =VLOOKUP($A14&F$3&F$1,DB!$A:$J,10,0) -> 0.3045 | G14: =VLOOKUP($A14&G$3&G$1,DB!$A:$J,10,0) -> 0.2771 | H14: =VLOOKUP($A14&H$3&H$1,DB!$A:$J,10,0) -> 0.2676 | I14: =VLOOKUP($A14&I$3&I$1,DB!$A:$J,10,0) -> 0.2731 | ... EK14: =VLOOKUP($A14&EK$3&EK$1,DB!$A:$J,10,0) -> 1744.7
A15: Machacalis | B15: =VLOOKUP($A15&B$3&B$1,DB!$A:$J,10,0) -> 0.2538 | C15: =VLOOKUP($A15&C$3&C$1,DB!$A:$J,10,0) -> 0.2991 | D15: =VLOOKUP($A15&D$3&D$1,DB!$A:$J,10,0) -> 0.2607 | E15: =VLOOKUP($A15&E$3&E$1,DB!$A:$J,10,0) -> 0.2935 | F15: =VLOOKUP($A15&F$3&F$1,DB!$A:$J,10,0) -> 0.2594 | G15: =VLOOKUP($A15&G$3&G$1,DB!$A:$J,10,0) -> 0.2791 | H15: =VLOOKUP($A15&H$3&H$1,DB!$A:$J,10,0) -> 0.2209 | I15: =VLOOKUP($A15&I$3&I$1,DB!$A:$J,10,0) -> 0.2602 | ... EK15: =VLOOKUP($A15&EK$3&EK$1,DB!$A:$J,10,0) -> #N/A
... A26: Umburatiba | B26: =VLOOKUP($A26&B$3&B$1,DB!$A:$J,10,0) -> 0.2686 | C26: =VLOOKUP($A26&C$3&C$1,DB!$A:$J,10,0) -> 0.2565 | D26: =VLOOKUP($A26&D$3&D$1,DB!$A:$J,10,0) -> 0.2955 | E26: =VLOOKUP($A26&E$3&E$1,DB!$A:$J,10,0) -> 0.2744 | F26: =VLOOKUP($A26&F$3&F$1,DB!$A:$J,10,0) -> 0.2645 | G26: =VLOOKUP($A26&G$3&G$1,DB!$A:$J,10,0) -> 0.2771 | H26: =VLOOKUP($A26&H$3&H$1,DB!$A:$J,10,0) -> 0.2217 | I26: =VLOOKUP($A26&I$3&I$1,DB!$A:$J,10,0) -> 0.2502 | ... EK26: =VLOOKUP($A26&EK$3&EK$1,DB!$A:$J,10,0) -> 0
